Metadata-Version: 2.4
Name: zenith-web
Version: 0.3.0
Summary: Modern Python web framework with clean architecture and type-safe dependency injection
Project-URL: Homepage, https://github.com/nijaru/zenith
Project-URL: Documentation, https://nijaru.github.io/zenith
Project-URL: Repository, https://github.com/nijaru/zenith.git
Project-URL: Issues, https://github.com/nijaru/zenith/issues
Author-email: Nick Russo <nijaru7@gmail.com>
License: MIT
License-File: LICENSE
Keywords: framework,http3,liveview,quic,realtime,web,websockets
Classifier: Development Status :: 3 - Alpha
Classifier: Intended Audience :: Developers
Classifier: License :: OSI Approved :: MIT License
Classifier: Programming Language :: Python :: 3
Classifier: Programming Language :: Python :: 3.12
Classifier: Programming Language :: Python :: 3.13
Classifier: Topic :: Internet :: WWW/HTTP :: Dynamic Content
Classifier: Topic :: Software Development :: Libraries :: Application Frameworks
Requires-Python: <3.13,>=3.12
Requires-Dist: aiosqlite>=0.19.0
Requires-Dist: alembic>=1.13.0
Requires-Dist: asyncpg>=0.29.0
Requires-Dist: bcrypt>=4.1.0
Requires-Dist: click>=8.1.0
Requires-Dist: greenlet>=3.2.4
Requires-Dist: jinja2>=3.1.0
Requires-Dist: msgspec>=0.19.0
Requires-Dist: orjson>=3.11.3
Requires-Dist: passlib[bcrypt]>=1.7.4
Requires-Dist: prometheus-client>=0.22.1
Requires-Dist: psutil>=7.0.0
Requires-Dist: pydantic>=2.11.9
Requires-Dist: pyjwt>=2.8.0
Requires-Dist: python-multipart>=0.0.6
Requires-Dist: redis>=5.0.0
Requires-Dist: sqlalchemy>=2.0.0
Requires-Dist: sqlmodel>=0.0.22
Requires-Dist: starlette>=0.32.0
Requires-Dist: structlog>=23.0.0
Requires-Dist: uvicorn[standard]>=0.24.0
Requires-Dist: uvloop>=0.21.0
Requires-Dist: websockets>=12.0
Provides-Extra: benchmark
Requires-Dist: aiosqlite>=0.19.0; extra == 'benchmark'
Requires-Dist: fastapi>=0.104.0; extra == 'benchmark'
Requires-Dist: flask-sqlalchemy>=3.1.0; extra == 'benchmark'
Requires-Dist: flask>=3.0.0; extra == 'benchmark'
Requires-Dist: httpx>=0.25.0; extra == 'benchmark'
Requires-Dist: psutil>=5.9.0; extra == 'benchmark'
Provides-Extra: compression
Requires-Dist: brotli>=1.1.0; extra == 'compression'
Requires-Dist: zstandard>=0.23.0; extra == 'compression'
Provides-Extra: dev
Requires-Dist: httpx>=0.25.0; extra == 'dev'
Requires-Dist: ipdb>=0.13.0; extra == 'dev'
Requires-Dist: pyright>=1.1.350; extra == 'dev'
Requires-Dist: pytest-asyncio>=0.21.0; extra == 'dev'
Requires-Dist: pytest-cov>=4.1.0; extra == 'dev'
Requires-Dist: pytest>=7.4.0; extra == 'dev'
Requires-Dist: ruff>=0.1.6; extra == 'dev'
Provides-Extra: http3
Requires-Dist: aioquic>=1.2.0; extra == 'http3'
Requires-Dist: cryptography>=42.0.0; extra == 'http3'
Provides-Extra: performance
Requires-Dist: msgspec>=0.18.0; extra == 'performance'
